L_graph_system/__init__.py
L_graph_system/arc.py
L_graph_system/lgraph.py
L_graph_system/vertex.py
L_graph_system-0.1.1.dist-info/LICENSE
L_graph_system-0.1.1.dist-info/METADATA
L_graph_system-0.1.1.dist-info/WHEEL
L_graph_system-0.1.1.dist-info/top_level.txt
L_graph_system-0.1.1.dist-info/RECORD
