Metadata-Version: 2.1
Name: L-graph-system
Version: 0.1.1
Summary: A package to work with L-graphs
Home-page: https://github.com/RaidenSA/L-graph_system
Author: Konstantin Saurin
Author-email: tasoshka654@gmail.com
License: UNKNOWN
Project-URL: Bug Tracker, https://github.com/RaidenSA/L-graph_system/issues
Platform: UNKNOWN
Classifier: Programming Language :: Python :: 3
Classifier: License :: OSI Approved :: MIT License
Classifier: Operating System :: OS Independent
Requires-Python: >=3.6
